DescKGC/__init__.py
DescKGC/procedures/__init__.py
DescKGC/procedures/align_across_subgraphs/__init__.py
DescKGC/procedures/align_across_subgraphs/base.py
DescKGC/procedures/align_across_subgraphs/utils.py
DescKGC/procedures/build_config/__init__.py
DescKGC/procedures/build_config/base.py
DescKGC/procedures/extract_and_insert/__init__.py
DescKGC/procedures/extract_and_insert/base.py
DescKGC/procedures/extract_and_insert/utils.py
DescKGC/procedures/sync_embedding/__init__.py
DescKGC/procedures/sync_embedding/base.py
DescKGC/scripts/__init__.py
DescKGC/scripts/add_from_arxiv.py
DescKGC/scripts/cli.py
DescKGC/scripts/entity_alignment.py
DescKGC/scripts/extract_entity_from_doc.py
DescKGC/scripts/manage_config.py
DescKGC/scripts/manage_db.py
DescKGC/scripts/search_from_arxiv.py
DescKGC/tools/__init__.py
DescKGC/tools/align/__init__.py
DescKGC/tools/align/base.py
DescKGC/tools/align/parser.py
DescKGC/tools/align/template.py
DescKGC/tools/align/utils.py
DescKGC/tools/arxiv/__init__.py
DescKGC/tools/arxiv/arxiv_data.py
DescKGC/tools/arxiv/base.py
DescKGC/tools/chroma/__init__.py
DescKGC/tools/chroma/base.py
DescKGC/tools/config_manager/__init__.py
DescKGC/tools/config_manager/base.py
DescKGC/tools/config_manager/default_config.py
DescKGC/tools/db_manager/__init__.py
DescKGC/tools/db_manager/base.py
DescKGC/tools/db_manager/type.py
DescKGC/tools/db_manager/utils.py
DescKGC/tools/extractor/__init__.py
DescKGC/tools/extractor/base.py
DescKGC/tools/extractor/template.py
DescKGC/tools/neo4j/__init__.py
DescKGC/tools/neo4j/base.py
DescKGC/tools/neo4j/cypher_template.py
DescKGC/tools/neo4j/utils.py
desckgc-0.0.7.dist-info/entry_points.txt
desckgc-0.0.7.dist-info/METADATA
desckgc-0.0.7.dist-info/WHEEL
desckgc-0.0.7.dist-info/RECORD
